data_to_xml/__init__.py
data_to_xml/py.typed
data_to_xml/version.py
data_to_xml/xml_converter.py
data_to_xml-1.0.9.dist-info/LICENSE
data_to_xml-1.0.9.dist-info/METADATA
data_to_xml-1.0.9.dist-info/WHEEL
data_to_xml-1.0.9.dist-info/entry_points.txt
data_to_xml-1.0.9.dist-info/top_level.txt
data_to_xml-1.0.9.dist-info/RECORD
