Metadata-Version: 2.1
Name: data-to-xml
Version: 1.0.9
Summary: A simple dict to xml converter
Author: Thomas William
Author-email: Reimund Järnfors <reimund@code7.se>, Adam Nogowski <anogowski@live.com>
Maintainer-email: Adam Nogowski <anogowski@live.com>
License: Dual License: All software and documentation is distributed under "BSD 3-Clause License" AND "Mozilla Public License Version 2.0"
Project-URL: Repository, https://github.com/anogowski/data-to-xml
Keywords: dict,xml,list,data,structure,convert,dictionary
Classifier: Development Status :: 5 - Production/Stable
Classifier: Intended Audience :: Developers
Classifier: Operating System :: OS Independent
Classifier: Programming Language :: Python
Classifier: Programming Language :: Python :: 3.11
Classifier: Programming Language :: Python :: 3.12
Classifier: Programming Language :: Python :: 3.13
Classifier: Programming Language :: Python :: 3 :: Only
Classifier: Programming Language :: Python :: Implementation :: CPython
Classifier: Programming Language :: Python :: Implementation :: PyPy
Classifier: License :: OSI Approved :: BSD License
Classifier: License :: OSI Approved :: Mozilla Public License 2.0 (MPL 2.0)
Requires-Python: >=3.11
License-File: LICENSE
